generate/__init__.py
generate/api/__init__.py
generate/api/generator.py
pytdlib/__init__.py
pytdlib/version.py
pytdlib/api/__init__.py
pytdlib/api/errors/__init__.py
pytdlib/api/errors/error.py
pytdlib/api/utils/__init__.py
pytdlib/api/utils/all_types.py
pytdlib/api/utils/object.py
pytdlib/app/__init__.py
pytdlib/app/telegram.py
pytdlib/app/dispatcher/__init__.py
pytdlib/app/dispatcher/dispatcher.py
pytdlib/app/events/__init__.py
pytdlib/app/events/update.py
pytdlib/app/filters/__init__.py
pytdlib/app/methods/__init__.py
pytdlib/app/methods/auth/__init__.py
pytdlib/app/methods/auth/check_bot_token.py
pytdlib/app/methods/auth/check_darabase_key.py
pytdlib/app/methods/auth/send_code_request.py
pytdlib/app/methods/auth/set_database_key.py
pytdlib/app/methods/auth/set_tdlib_parameters.py
pytdlib/app/methods/auth/sign_in.py
pytdlib/app/methods/auth/sign_up.py
pytdlib/app/methods/proxy/__init__.py
pytdlib/app/methods/proxy/add_proxy.py
pytdlib/app/methods/proxy/get_proxies.py
pytdlib/app/methods/proxy/ping_proxy.py
pytdlib/app/methods/proxy/remove_proxy.py
pytdlib/app/methods/user/__init__.py
pytdlib/app/methods/user/get_me.py
pytdlib/app/types/__init__.py
pytdlib/app/types/proxy/__init__.py
pytdlib/app/types/proxy/http_proxy.py
pytdlib/app/types/proxy/mtproto_proxy.py
pytdlib/app/types/proxy/proxy.py
pytdlib/app/types/proxy/socks5_ptoxy.py
pytdlib/app/utils/__init__.py
pytdlib/app/utils/base_telegram.py
pytdlib/app/utils/callback.py
pytdlib/app/utils/msg_id.py
pytdlib/app/utils/result.py
pytdlib/td/__init__.py
pytdlib/td/td.py
pytdlib/td/client/__init__.py
pytdlib/td/client/client.py
pytdlib/td/client/json_client/__init__.py
pytdlib/td/client/json_client/json_client.py
pytdlib/td/log/__init__.py
pytdlib/td/log/log.py
pytdlib/utils/__init__.py
pytdlib/utils/authorization_stats.py
Pytdlib-0.1.8.dist-info/LICENSE
Pytdlib-0.1.8.dist-info/METADATA
Pytdlib-0.1.8.dist-info/WHEEL
Pytdlib-0.1.8.dist-info/top_level.txt
Pytdlib-0.1.8.dist-info/RECORD
